rko_lio-0.1.7.dist-info/RECORD
rko_lio-0.1.7.dist-info/WHEEL
rko_lio-0.1.7.dist-info/entry_points.txt
rko_lio-0.1.7.dist-info/METADATA
rko_lio/rko_lio.rbl
rko_lio/util.py
rko_lio/scoped_profiler.py
rko_lio/__init__.py
rko_lio/lio_pipeline.py
rko_lio/lio.py
rko_lio/cli.py
rko_lio/rko_lio_pybind.cpython-314-darwin.so
rko_lio/dataloaders/helipr_file_reader_pybind.cpython-314-darwin.so
rko_lio/dataloaders/raw.py
rko_lio/dataloaders/__init__.py
rko_lio/dataloaders/rosbag.py
rko_lio/dataloaders/helipr.py
rko_lio/dataloaders/get_dataloader.py
rko_lio/dataloaders/utils/__init__.py
rko_lio/dataloaders/utils/static_tf_tree.py
rko_lio/dataloaders/utils/ros_read_point_cloud.py
