Metadata-Version: 2.2
Name: rko_lio
Version: 0.1.7
Summary: A Robust Approach for LiDAR-Inertial Odometry Without Sensor-Specific Modelling
Keywords: LiDAR,IMU,Odometry,Localization,SLAM
Author-Email: Meher Malladi <rm.meher97@gmail.com>
License: MIT
Classifier: Intended Audience :: Developers
Classifier: Intended Audience :: Education
Classifier: Intended Audience :: Other Audience
Classifier: Intended Audience :: Science/Research
Classifier: Programming Language :: C++
Classifier: Programming Language :: Python :: 3
Classifier: Programming Language :: Python :: 3.10
Classifier: Programming Language :: Python :: 3.11
Classifier: Programming Language :: Python :: 3.12
Classifier: Programming Language :: Python :: 3.13
Classifier: Programming Language :: Python :: 3.14
Classifier: Operating System :: Unix
Project-URL: Homepage, https://github.com/PRBonn/rko_lio
Requires-Python: >=3.10
Requires-Dist: numpy~=2.2
Requires-Dist: typer<0.21,>=0.19
Requires-Dist: pyyaml~=6.0
Requires-Dist: pyquaternion<0.10,>=0.9
Requires-Dist: tqdm~=4.67
Provides-Extra: all
Requires-Dist: open3d<0.20,>=0.18; extra == "all"
Requires-Dist: rerun-sdk<0.27,>=0.24; extra == "all"
Requires-Dist: rosbags<0.12,>=0.10; extra == "all"
Requires-Dist: pytest~=8.4; extra == "all"
